<?xml version='1.0' encoding='UTF-8'?>
<rdf:RDF xmlns:rdf="http://www.w3.org/1999/02/22-rdf-syntax-ns#" xmlns:prism="http://prismstandard.org/namespaces/basic/2.0/" xmlns:dc="http://purl.org/dc/elements/1.1/" xmlns:syn="http://purl.org/rss/1.0/modules/syndication/" xmlns:content="http://purl.org/rss/1.0/modules/content/" xmlns="http://purl.org/rss/1.0/">
  <channel rdf:about="http://journals.aps.org/prb/">
    <title>Recent Articles in Phys. Rev. B</title>
    <link>http://journals.aps.org/prb/</link>
    <description>Recent articles in Physical Review B</description>
    <syn:updatePeriod>hourly</syn:updatePeriod>
    <syn:updateFrequency>1</syn:updateFrequency>
    <syn:updateBase>2026-01-21T01:16:32+00:00</syn:updateBase>
    <dc:creator>rss@aps.org</dc:creator>
    <dc:publisher>assocpub@aps.org</dc:publisher>
    <dc:date>2026-01-21T01:16:32+00:00</dc:date>
    <dc:language>en</dc:language>
    <dc:rights>Copyright © 2026 the American Physical Society. Personal use only, all commercial or other reuse prohibited</dc:rights>
    <prism:copyright>Copyright © 2026 the American Physical Society</prism:copyright>
    <prism:rightsAgent>assocpub@aps.org</prism:rightsAgent>
    <items>
      <rdf:Seq>
        <rdf:li rdf:resource="http://link.aps.org/doi/10.1103/ncm1-rfsn"/>
        <rdf:li rdf:resource="http://link.aps.org/doi/10.1103/t8nh-qdyl"/>
        <rdf:li rdf:resource="http://link.aps.org/doi/10.1103/xknq-czll"/>
        <rdf:li rdf:resource="http://link.aps.org/doi/10.1103/j9mv-75ls"/>
        <rdf:li rdf:resource="http://link.aps.org/doi/10.1103/by2b-wxfq"/>
        <rdf:li rdf:resource="http://link.aps.org/doi/10.1103/ld4p-hl13"/>
        <rdf:li rdf:resource="http://link.aps.org/doi/10.1103/7j4m-g6nh"/>
        <rdf:li rdf:resource="http://link.aps.org/doi/10.1103/2q6v-4brs"/>
        <rdf:li rdf:resource="http://link.aps.org/doi/10.1103/m5wt-1hx4"/>
        <rdf:li rdf:resource="http://link.aps.org/doi/10.1103/5fp5-xd6m"/>
        <rdf:li rdf:resource="http://link.aps.org/doi/10.1103/gt73-dggf"/>
        <rdf:li rdf:resource="http://link.aps.org/doi/10.1103/q2lp-ffhf"/>
        <rdf:li rdf:resource="http://link.aps.org/doi/10.1103/jnjq-clrk"/>
        <rdf:li rdf:resource="http://link.aps.org/doi/10.1103/pt16-43yd"/>
        <rdf:li rdf:resource="http://link.aps.org/doi/10.1103/jyfh-q2r7"/>
        <rdf:li rdf:resource="http://link.aps.org/doi/10.1103/blkg-3t1v"/>
        </rdf:Seq>
    </items>
  </channel>
  <item rdf:about="http://link.aps.org/doi/10.1103/ncm1-rfsn">
    <title>Single crystal growth, structural and physical properties, and absence of a charge density wave in ${\mathrm{Ti}}_{0.85}{\mathrm{Fe}}_{6}{\mathrm{Ge}}_{6}$</title>
    <link>http://link.aps.org/doi/10.1103/ncm1-rfsn</link>
    <description>Author(s): Dechao Cheng, Nour Maraytta, Xiuhua Chen, Xizhi Li, Xueliang Wu, Xiangxiang Jing, Yong Hu, Youpin Gong, Mingquan He, Yisheng Chai, Xiaoyuan Zhou, Pengfei Jiang, Yilin Wang, Michael Merz, and Aifeng Wang&lt;br/&gt;&lt;p&gt;The rattling chain model predicts CDWs in &lt;math xmlns="http://www.w3.org/1998/Math/MathML" display="inline"&gt;&lt;mrow&gt;&lt;mi&gt;A&lt;/mi&gt;&lt;mspace width="0"&gt;&lt;/mspace&gt;&lt;msub&gt;&lt;mi&gt;M&lt;/mi&gt;&lt;mn&gt;6&lt;/mn&gt;&lt;/msub&gt;&lt;mspace width="0"&gt;&lt;/mspace&gt;&lt;msub&gt;&lt;mi&gt;X&lt;/mi&gt;&lt;mn&gt;6&lt;/mn&gt;&lt;/msub&gt;&lt;/mrow&gt;&lt;/math&gt; kagome compounds with small filler atoms &lt;math xmlns="http://www.w3.org/1998/Math/MathML" display="inline"&gt;&lt;mi&gt;A&lt;/mi&gt;&lt;/math&gt; embedded in a large &lt;math xmlns="http://www.w3.org/1998/Math/MathML" display="inline"&gt;&lt;mrow&gt;&lt;msub&gt;&lt;mi&gt;M&lt;/mi&gt;&lt;mn&gt;6&lt;/mn&gt;&lt;/msub&gt;&lt;mspace width="0"&gt;&lt;/mspace&gt;&lt;msub&gt;&lt;mi&gt;X&lt;/mi&gt;&lt;mn&gt;6&lt;/mn&gt;&lt;/msub&gt;&lt;/mrow&gt;&lt;/math&gt; host. Here, despite Ti being a small filler atom, the authors observe no CDW in Ti&lt;math xmlns="http://www.w3.org/1998/Math/MathML" display="inline"&gt;&lt;msub&gt;&lt;mrow&gt;&lt;/mrow&gt;&lt;mrow&gt;&lt;mn&gt;0&lt;/mn&gt;&lt;mo lspace="0" rspace="0"&gt;.&lt;/mo&gt;&lt;mn&gt;85&lt;/mn&gt;&lt;/mrow&gt;&lt;/msub&gt;&lt;/math&gt;Fe&lt;math xmlns="http://www.w3.org/1998/Math/MathML" display="inline"&gt;&lt;msub&gt;&lt;mrow&gt;&lt;/mrow&gt;&lt;mn&gt;6&lt;/mn&gt;&lt;/msub&gt;&lt;/math&gt;Ge&lt;math xmlns="http://www.w3.org/1998/Math/MathML" display="inline"&gt;&lt;msub&gt;&lt;mrow&gt;&lt;/mrow&gt;&lt;mn&gt;6&lt;/mn&gt;&lt;/msub&gt;&lt;/math&gt;. Through in-depth electronic structure and bonding analyses, they demonstrate that, in addition to ionic radius, the bonding characteristics of the filler atom are crucial for CDW formation. This finding significantly extends the rattling chain model, offering new insights into the factors driving CDW transitions in kagome materials.&lt;/p&gt;&lt;img src="//cdn.journals.aps.org/journals/PRB/key_images/10.1103/ncm1-rfsn.png" width="200" height=\"100\"&gt;&lt;br/&gt;[Phys. Rev. B 113, 035133] Published Tue Jan 20, 2026</description>
    <content:encoded>&lt;p&gt;Author(s): Dechao Cheng, Nour Maraytta, Xiuhua Chen, Xizhi Li, Xueliang Wu, Xiangxiang Jing, Yong Hu, Youpin Gong, Mingquan He, Yisheng Chai, Xiaoyuan Zhou, Pengfei Jiang, Yilin Wang, Michael Merz, and Aifeng Wang&lt;/p&gt;&lt;p&gt;The rattling chain model predicts CDWs in &lt;math xmlns="http://www.w3.org/1998/Math/MathML" display="inline"&gt;&lt;mrow&gt;&lt;mi&gt;A&lt;/mi&gt;&lt;mspace width="0"&gt;&lt;/mspace&gt;&lt;msub&gt;&lt;mi&gt;M&lt;/mi&gt;&lt;mn&gt;6&lt;/mn&gt;&lt;/msub&gt;&lt;mspace width="0"&gt;&lt;/mspace&gt;&lt;msub&gt;&lt;mi&gt;X&lt;/mi&gt;&lt;mn&gt;6&lt;/mn&gt;&lt;/msub&gt;&lt;/mrow&gt;&lt;/math&gt; kagome compounds with small filler atoms &lt;math xmlns="http://www.w3.org/1998/Math/MathML" display="inline"&gt;&lt;mi&gt;A&lt;/mi&gt;&lt;/math&gt; embedded in a large &lt;math xmlns="http://www.w3.org/1998/Math/MathML" display="inline"&gt;&lt;mrow&gt;&lt;msub&gt;&lt;mi&gt;M&lt;/mi&gt;&lt;mn&gt;6&lt;/mn&gt;&lt;/msub&gt;&lt;mspace width="0"&gt;&lt;/mspace&gt;&lt;msub&gt;&lt;mi&gt;X&lt;/mi&gt;&lt;mn&gt;6&lt;/mn&gt;&lt;/msub&gt;&lt;/mrow&gt;&lt;/math&gt; host. Here, despite Ti being a small filler atom, the authors observe no CDW in Ti&lt;math xmlns="http://www.w3.org/1998/Math/MathML" display="inline"&gt;&lt;msub&gt;&lt;mrow&gt;&lt;/mrow&gt;&lt;mrow&gt;&lt;mn&gt;0&lt;/mn&gt;&lt;mo lspace="0" rspace="0"&gt;.&lt;/mo&gt;&lt;mn&gt;85&lt;/mn&gt;&lt;/mrow&gt;&lt;/msub&gt;&lt;/math&gt;Fe&lt;math xmlns="http://www.w3.org/1998/Math/MathML" display="inline"&gt;&lt;msub&gt;&lt;mrow&gt;&lt;/mrow&gt;&lt;mn&gt;6&lt;/mn&gt;&lt;/msub&gt;&lt;/math&gt;Ge&lt;math xmlns="http://www.w3.org/1998/Math/MathML" display="inline"&gt;&lt;msub&gt;&lt;mrow&gt;&lt;/mrow&gt;&lt;mn&gt;6&lt;/mn&gt;&lt;/msub&gt;&lt;/math&gt;. Through in-depth electronic structure and bonding analyses, they demonstrate that, in addition to ionic radius, the bonding characteristics of the filler atom are crucial for CDW formation. This finding significantly extends the rattling chain model, offering new insights into the factors driving CDW transitions in kagome materials.&lt;/p&gt;&lt;img src="//cdn.journals.aps.org/journals/PRB/key_images/10.1103/ncm1-rfsn.png" width="200" height=\"100\"&gt;&lt;br/&gt;&lt;p&gt;[Phys. Rev. B 113, 035133] Published Tue Jan 20, 2026&lt;/p&gt;</content:encoded>
    <dc:title>Single crystal growth, structural and physical properties, and absence of a charge density wave in ${\mathrm{Ti}}_{0.85}{\mathrm{Fe}}_{6}{\mathrm{Ge}}_{6}$</dc:title>
    <dc:creator>Dechao Cheng, Nour Maraytta, Xiuhua Chen, Xizhi Li, Xueliang Wu, Xiangxiang Jing, Yong Hu, Youpin Gong, Mingquan He, Yisheng Chai, Xiaoyuan Zhou, Pengfei Jiang, Yilin Wang, Michael Merz, and Aifeng Wang</dc:creator>
    <dc:date>2026-01-20T10:00:00+00:00</dc:date>
    <dc:rights>Personal use only, all commercial or other reuse prohibited</dc:rights>
    <dc:source>Phys. Rev. B 113, 035133 (2026)</dc:source>
    <dc:type>article</dc:type>
    <dc:identifier>doi:10.1103/ncm1-rfsn</dc:identifier>
    <prism:doi>10.1103/ncm1-rfsn</prism:doi>
    <prism:publicationName>Physical Review B</prism:publicationName>
    <prism:volume>113</prism:volume>
    <prism:number>3</prism:number>
    <prism:publicationDate>2026-01-20T10:00:00+00:00</prism:publicationDate>
    <prism:url>http://link.aps.org/doi/10.1103/ncm1-rfsn</prism:url>
    <prism:startingPage>035133</prism:startingPage>
    <dc:subject>Electronic structure and strongly correlated systems</dc:subject>
    <prism:section>Electronic structure and strongly correlated systems</prism:section>
  </item>
  <item rdf:about="http://link.aps.org/doi/10.1103/t8nh-qdyl">
    <title>Filling-dependent phase competition in the interacting kagome flat band system</title>
    <link>http://link.aps.org/doi/10.1103/t8nh-qdyl</link>
    <description>Author(s): Kevin J. U. Vidarte, R. Cardias, and A. Latgé&lt;br/&gt;&lt;p&gt;The kagome lattice, known for its geometric frustration and flat bands, provides a fertile ground for emerging correlated electronic phases. Using a self-consistent mean-field approach within the extended Hubbard model, we compute the phase diagrams of the kagome lattice as a function of on-site and…&lt;/p&gt;&lt;br/&gt;[Phys. Rev. B 113, 035134] Published Tue Jan 20, 2026</description>
    <content:encoded>&lt;p&gt;Author(s): Kevin J. U. Vidarte, R. Cardias, and A. Latgé&lt;/p&gt;&lt;p&gt;The kagome lattice, known for its geometric frustration and flat bands, provides a fertile ground for emerging correlated electronic phases. Using a self-consistent mean-field approach within the extended Hubbard model, we compute the phase diagrams of the kagome lattice as a function of on-site and…&lt;/p&gt;&lt;br/&gt;&lt;p&gt;[Phys. Rev. B 113, 035134] Published Tue Jan 20, 2026&lt;/p&gt;</content:encoded>
    <dc:title>Filling-dependent phase competition in the interacting kagome flat band system</dc:title>
    <dc:creator>Kevin J. U. Vidarte, R. Cardias, and A. Latgé</dc:creator>
    <dc:date>2026-01-20T10:00:00+00:00</dc:date>
    <dc:rights>Personal use only, all commercial or other reuse prohibited</dc:rights>
    <dc:source>Phys. Rev. B 113, 035134 (2026)</dc:source>
    <dc:type>article</dc:type>
    <dc:identifier>doi:10.1103/t8nh-qdyl</dc:identifier>
    <prism:doi>10.1103/t8nh-qdyl</prism:doi>
    <prism:publicationName>Physical Review B</prism:publicationName>
    <prism:volume>113</prism:volume>
    <prism:number>3</prism:number>
    <prism:publicationDate>2026-01-20T10:00:00+00:00</prism:publicationDate>
    <prism:url>http://link.aps.org/doi/10.1103/t8nh-qdyl</prism:url>
    <prism:startingPage>035134</prism:startingPage>
    <dc:subject>Electronic structure and strongly correlated systems</dc:subject>
    <prism:section>Electronic structure and strongly correlated systems</prism:section>
  </item>
  <item rdf:about="http://link.aps.org/doi/10.1103/xknq-czll">
    <title>Engineering Hubbard models with gated two-dimensional moiré systems</title>
    <link>http://link.aps.org/doi/10.1103/xknq-czll</link>
    <description>Author(s): Yiqi Yang (杨怡奇), Yubo Yang (杨煜波), Miguel A. Morales, and Shiwei Zhang&lt;br/&gt;&lt;p&gt;Lattice models are powerful tools for studying strongly correlated quantum many-body systems, but their general lack of exact solutions motivates efforts to simulate them in tunable platforms. Recently, a promising new candidate has emerged for such platforms from two-dimensional materials. A subset…&lt;/p&gt;&lt;br/&gt;[Phys. Rev. B 113, 035135] Published Tue Jan 20, 2026</description>
    <content:encoded>&lt;p&gt;Author(s): Yiqi Yang (杨怡奇), Yubo Yang (杨煜波), Miguel A. Morales, and Shiwei Zhang&lt;/p&gt;&lt;p&gt;Lattice models are powerful tools for studying strongly correlated quantum many-body systems, but their general lack of exact solutions motivates efforts to simulate them in tunable platforms. Recently, a promising new candidate has emerged for such platforms from two-dimensional materials. A subset…&lt;/p&gt;&lt;br/&gt;&lt;p&gt;[Phys. Rev. B 113, 035135] Published Tue Jan 20, 2026&lt;/p&gt;</content:encoded>
    <dc:title>Engineering Hubbard models with gated two-dimensional moiré systems</dc:title>
    <dc:creator>Yiqi Yang (杨怡奇), Yubo Yang (杨煜波), Miguel A. Morales, and Shiwei Zhang</dc:creator>
    <dc:date>2026-01-20T10:00:00+00:00</dc:date>
    <dc:rights>Personal use only, all commercial or other reuse prohibited</dc:rights>
    <dc:source>Phys. Rev. B 113, 035135 (2026)</dc:source>
    <dc:type>article</dc:type>
    <dc:identifier>doi:10.1103/xknq-czll</dc:identifier>
    <prism:doi>10.1103/xknq-czll</prism:doi>
    <prism:publicationName>Physical Review B</prism:publicationName>
    <prism:volume>113</prism:volume>
    <prism:number>3</prism:number>
    <prism:publicationDate>2026-01-20T10:00:00+00:00</prism:publicationDate>
    <prism:url>http://link.aps.org/doi/10.1103/xknq-czll</prism:url>
    <prism:startingPage>035135</prism:startingPage>
    <dc:subject>Electronic structure and strongly correlated systems</dc:subject>
    <prism:section>Electronic structure and strongly correlated systems</prism:section>
  </item>
  <item rdf:about="http://link.aps.org/doi/10.1103/j9mv-75ls">
    <title>Phases and criticality of the triangular lattice $\mathrm{SU}(N)$ Hofstadter-Hubbard model</title>
    <link>http://link.aps.org/doi/10.1103/j9mv-75ls</link>
    <description>Author(s): Lu Zhang, Rongning Liu, and Xue-Yang Song&lt;br/&gt;&lt;p&gt;We report the study of phases and transitions of the $\text{SU}(N)$ Hofstadter-Hubbard model subject to a commensurate magnetic field on the triangular lattice. At filling one fermion per site, for the number of fermion flavors $2≤N≤8$, we identify three distinct phases and calculate critical intera…&lt;/p&gt;&lt;br/&gt;[Phys. Rev. B 113, 045131] Published Tue Jan 20, 2026</description>
    <content:encoded>&lt;p&gt;Author(s): Lu Zhang, Rongning Liu, and Xue-Yang Song&lt;/p&gt;&lt;p&gt;We report the study of phases and transitions of the &lt;math xmlns="http://www.w3.org/1998/Math/MathML"&gt;&lt;mrow&gt;&lt;mtext&gt;SU&lt;/mtext&gt;&lt;mo&gt;(&lt;/mo&gt;&lt;mi&gt;N&lt;/mi&gt;&lt;mo&gt;)&lt;/mo&gt;&lt;/mrow&gt;&lt;/math&gt; Hofstadter-Hubbard model subject to a commensurate magnetic field on the triangular lattice. At filling one fermion per site, for the number of fermion flavors &lt;math xmlns="http://www.w3.org/1998/Math/MathML"&gt;&lt;mrow&gt;&lt;mn&gt;2&lt;/mn&gt;&lt;mo&gt;≤&lt;/mo&gt;&lt;mi&gt;N&lt;/mi&gt;&lt;mo&gt;≤&lt;/mo&gt;&lt;mn&gt;8&lt;/mn&gt;&lt;/mrow&gt;&lt;/math&gt;, we identify three distinct phases and calculate critical interaction stren…&lt;/p&gt;&lt;br/&gt;&lt;p&gt;[Phys. Rev. B 113, 045131] Published Tue Jan 20, 2026&lt;/p&gt;</content:encoded>
    <dc:title>Phases and criticality of the triangular lattice $\mathrm{SU}(N)$ Hofstadter-Hubbard model</dc:title>
    <dc:creator>Lu Zhang, Rongning Liu, and Xue-Yang Song</dc:creator>
    <dc:date>2026-01-20T10:00:00+00:00</dc:date>
    <dc:rights>Personal use only, all commercial or other reuse prohibited</dc:rights>
    <dc:source>Phys. Rev. B 113, 045131 (2026)</dc:source>
    <dc:type>article</dc:type>
    <dc:identifier>doi:10.1103/j9mv-75ls</dc:identifier>
    <prism:doi>10.1103/j9mv-75ls</prism:doi>
    <prism:publicationName>Physical Review B</prism:publicationName>
    <prism:volume>113</prism:volume>
    <prism:number>4</prism:number>
    <prism:publicationDate>2026-01-20T10:00:00+00:00</prism:publicationDate>
    <prism:url>http://link.aps.org/doi/10.1103/j9mv-75ls</prism:url>
    <prism:startingPage>045131</prism:startingPage>
    <dc:subject>Electronic structure and strongly correlated systems</dc:subject>
    <prism:section>Electronic structure and strongly correlated systems</prism:section>
  </item>
  <item rdf:about="http://link.aps.org/doi/10.1103/by2b-wxfq">
    <title>Emergent magnetism and spin liquids in an extended Hubbard model at fractional filling</title>
    <link>http://link.aps.org/doi/10.1103/by2b-wxfq</link>
    <description>Author(s): Zhenhao Song, Urban F. P. Seifert, Leon Balents, and Hong-Chen Jiang&lt;br/&gt;&lt;p&gt;Motivated by twisted transition metal dichalcogenides (TMDs), we study an extended Hubbard model with both onsite and off-site repulsive interactions, in which Mott insulating states with concomitant charge order occur at fractional fillings. To resolve the charge ordering as well as the fate of the…&lt;/p&gt;&lt;br/&gt;[Phys. Rev. B 113, 045132] Published Tue Jan 20, 2026</description>
    <content:encoded>&lt;p&gt;Author(s): Zhenhao Song, Urban F. P. Seifert, Leon Balents, and Hong-Chen Jiang&lt;/p&gt;&lt;p&gt;Motivated by twisted transition metal dichalcogenides (TMDs), we study an extended Hubbard model with both onsite and off-site repulsive interactions, in which Mott insulating states with concomitant charge order occur at fractional fillings. To resolve the charge ordering as well as the fate of the…&lt;/p&gt;&lt;br/&gt;&lt;p&gt;[Phys. Rev. B 113, 045132] Published Tue Jan 20, 2026&lt;/p&gt;</content:encoded>
    <dc:title>Emergent magnetism and spin liquids in an extended Hubbard model at fractional filling</dc:title>
    <dc:creator>Zhenhao Song, Urban F. P. Seifert, Leon Balents, and Hong-Chen Jiang</dc:creator>
    <dc:date>2026-01-20T10:00:00+00:00</dc:date>
    <dc:rights>Personal use only, all commercial or other reuse prohibited</dc:rights>
    <dc:source>Phys. Rev. B 113, 045132 (2026)</dc:source>
    <dc:type>article</dc:type>
    <dc:identifier>doi:10.1103/by2b-wxfq</dc:identifier>
    <prism:doi>10.1103/by2b-wxfq</prism:doi>
    <prism:publicationName>Physical Review B</prism:publicationName>
    <prism:volume>113</prism:volume>
    <prism:number>4</prism:number>
    <prism:publicationDate>2026-01-20T10:00:00+00:00</prism:publicationDate>
    <prism:url>http://link.aps.org/doi/10.1103/by2b-wxfq</prism:url>
    <prism:startingPage>045132</prism:startingPage>
    <dc:subject>Electronic structure and strongly correlated systems</dc:subject>
    <prism:section>Electronic structure and strongly correlated systems</prism:section>
  </item>
  <item rdf:about="http://link.aps.org/doi/10.1103/ld4p-hl13">
    <title>Kramers nodal line in the charge density wave state of ${\mathrm{YTe}}_{3}$ and the influence of twin domains</title>
    <link>http://link.aps.org/doi/10.1103/ld4p-hl13</link>
    <description>Author(s): Shuvam Sarkar, Joydipto Bhattacharya, Pramod Bhakuni, Divya Jangra, Pampa Sadhukhan, Rajib Batabyal, Christos D. Malliakas, Marco Bianchi, Davide Curcio, Shubhankar Roy, Arnab Pariari, Sajal Barman, Mohammad Balal, Giovanni Di Santo, Luca Petaccia, Duck Young Chung, Yihao Wang, Vasant G. Sathe, Prabhat Mandal, Mercouri G. Kanatzidis, Philip Hofmann, Aparna Chakrabarti, and Sudipta Roy Barman&lt;br/&gt;&lt;p&gt;The authors demonstrate here that incommensurate charge density wave (CDW) driven inversion symmetry breaking in YTe&lt;math xmlns="http://www.w3.org/1998/Math/MathML" display="inline"&gt;&lt;msub&gt;&lt;mrow&gt;&lt;/mrow&gt;&lt;mn&gt;3&lt;/mn&gt;&lt;/msub&gt;&lt;/math&gt; produces a Kramers nodal line across the Brillouin zone. ARPES agrees well with &lt;math xmlns="http://www.w3.org/1998/Math/MathML" display="inline"&gt;&lt;mrow&gt;&lt;mi&gt;a&lt;/mi&gt;&lt;mspace width="0"&gt;&lt;/mspace&gt;&lt;mi&gt;b&lt;/mi&gt;&lt;/mrow&gt;&lt;/math&gt; &lt;math xmlns="http://www.w3.org/1998/Math/MathML" display="inline"&gt;&lt;mrow&gt;&lt;mi&gt;i&lt;/mi&gt;&lt;mspace width="0"&gt;&lt;/mspace&gt;&lt;mi&gt;n&lt;/mi&gt;&lt;mspace width="0"&gt;&lt;/mspace&gt;&lt;mi&gt;i&lt;/mi&gt;&lt;mspace width="0"&gt;&lt;/mspace&gt;&lt;mi&gt;t&lt;/mi&gt;&lt;mspace width="0"&gt;&lt;/mspace&gt;&lt;mi&gt;i&lt;/mi&gt;&lt;mspace width="0"&gt;&lt;/mspace&gt;&lt;mi&gt;o&lt;/mi&gt;&lt;/mrow&gt;&lt;/math&gt; band structure calculations when the CDW twin domains are considered. Consequently, symmetry-protected CDW shadow-band crossings with bilayer-split main bands that reach the Fermi level are identified. The noncentrosymmetric crystal structure has been established by x-ray crystallography and Raman spectroscopy. These findings establish YTe&lt;math xmlns="http://www.w3.org/1998/Math/MathML" display="inline"&gt;&lt;msub&gt;&lt;mrow&gt;&lt;/mrow&gt;&lt;mn&gt;3&lt;/mn&gt;&lt;/msub&gt;&lt;/math&gt; as a CDW-driven topological nodal-line metal.&lt;/p&gt;&lt;img src="//cdn.journals.aps.org/journals/PRB/key_images/10.1103/ld4p-hl13.png" width="200" height=\"100\"&gt;&lt;br/&gt;[Phys. Rev. B 113, 035129] Published Fri Jan 16, 2026</description>
    <content:encoded>&lt;p&gt;Author(s): Shuvam Sarkar, Joydipto Bhattacharya, Pramod Bhakuni, Divya Jangra, Pampa Sadhukhan, Rajib Batabyal, Christos D. Malliakas, Marco Bianchi, Davide Curcio, Shubhankar Roy, Arnab Pariari, Sajal Barman, Mohammad Balal, Giovanni Di Santo, Luca Petaccia, Duck Young Chung, Yihao Wang, Vasant G. Sathe, Prabhat Mandal, Mercouri G. Kanatzidis, Philip Hofmann, Aparna Chakrabarti, and Sudipta Roy Barman&lt;/p&gt;&lt;p&gt;The authors demonstrate here that incommensurate charge density wave (CDW) driven inversion symmetry breaking in YTe&lt;math xmlns="http://www.w3.org/1998/Math/MathML" display="inline"&gt;&lt;msub&gt;&lt;mrow&gt;&lt;/mrow&gt;&lt;mn&gt;3&lt;/mn&gt;&lt;/msub&gt;&lt;/math&gt; produces a Kramers nodal line across the Brillouin zone. ARPES agrees well with &lt;math xmlns="http://www.w3.org/1998/Math/MathML" display="inline"&gt;&lt;mrow&gt;&lt;mi&gt;a&lt;/mi&gt;&lt;mspace width="0"&gt;&lt;/mspace&gt;&lt;mi&gt;b&lt;/mi&gt;&lt;/mrow&gt;&lt;/math&gt; &lt;math xmlns="http://www.w3.org/1998/Math/MathML" display="inline"&gt;&lt;mrow&gt;&lt;mi&gt;i&lt;/mi&gt;&lt;mspace width="0"&gt;&lt;/mspace&gt;&lt;mi&gt;n&lt;/mi&gt;&lt;mspace width="0"&gt;&lt;/mspace&gt;&lt;mi&gt;i&lt;/mi&gt;&lt;mspace width="0"&gt;&lt;/mspace&gt;&lt;mi&gt;t&lt;/mi&gt;&lt;mspace width="0"&gt;&lt;/mspace&gt;&lt;mi&gt;i&lt;/mi&gt;&lt;mspace width="0"&gt;&lt;/mspace&gt;&lt;mi&gt;o&lt;/mi&gt;&lt;/mrow&gt;&lt;/math&gt; band structure calculations when the CDW twin domains are considered. Consequently, symmetry-protected CDW shadow-band crossings with bilayer-split main bands that reach the Fermi level are identified. The noncentrosymmetric crystal structure has been established by x-ray crystallography and Raman spectroscopy. These findings establish YTe&lt;math xmlns="http://www.w3.org/1998/Math/MathML" display="inline"&gt;&lt;msub&gt;&lt;mrow&gt;&lt;/mrow&gt;&lt;mn&gt;3&lt;/mn&gt;&lt;/msub&gt;&lt;/math&gt; as a CDW-driven topological nodal-line metal.&lt;/p&gt;&lt;img src="//cdn.journals.aps.org/journals/PRB/key_images/10.1103/ld4p-hl13.png" width="200" height=\"100\"&gt;&lt;br/&gt;&lt;p&gt;[Phys. Rev. B 113, 035129] Published Fri Jan 16, 2026&lt;/p&gt;</content:encoded>
    <dc:title>Kramers nodal line in the charge density wave state of ${\mathrm{YTe}}_{3}$ and the influence of twin domains</dc:title>
    <dc:creator>Shuvam Sarkar, Joydipto Bhattacharya, Pramod Bhakuni, Divya Jangra, Pampa Sadhukhan, Rajib Batabyal, Christos D. Malliakas, Marco Bianchi, Davide Curcio, Shubhankar Roy, Arnab Pariari, Sajal Barman, Mohammad Balal, Giovanni Di Santo, Luca Petaccia, Duck Young Chung, Yihao Wang, Vasant G. Sathe, Prabhat Mandal, Mercouri G. Kanatzidis, Philip Hofmann, Aparna Chakrabarti, and Sudipta Roy Barman</dc:creator>
    <dc:date>2026-01-16T10:00:00+00:00</dc:date>
    <dc:rights>Personal use only, all commercial or other reuse prohibited</dc:rights>
    <dc:source>Phys. Rev. B 113, 035129 (2026)</dc:source>
    <dc:type>article</dc:type>
    <dc:identifier>doi:10.1103/ld4p-hl13</dc:identifier>
    <prism:doi>10.1103/ld4p-hl13</prism:doi>
    <prism:publicationName>Physical Review B</prism:publicationName>
    <prism:volume>113</prism:volume>
    <prism:number>3</prism:number>
    <prism:publicationDate>2026-01-16T10:00:00+00:00</prism:publicationDate>
    <prism:url>http://link.aps.org/doi/10.1103/ld4p-hl13</prism:url>
    <prism:startingPage>035129</prism:startingPage>
    <dc:subject>Electronic structure and strongly correlated systems</dc:subject>
    <prism:section>Electronic structure and strongly correlated systems</prism:section>
  </item>
  <item rdf:about="http://link.aps.org/doi/10.1103/7j4m-g6nh">
    <title>Local electronic structure and magnetic properties of double-perovskite ${\mathrm{LaCo}}_{0.5}{\mathrm{Ni}}_{0.5}{\mathrm{O}}_{3}$ and ${\mathrm{PrCo}}_{0.5}{\mathrm{Ni}}_{0.5}{\mathrm{O}}_{3}$</title>
    <link>http://link.aps.org/doi/10.1103/7j4m-g6nh</link>
    <description>Author(s): Meng-Jie Huang, Peter Nagel, Andreas Eich, Michael Merz, and Stefan Schuppler&lt;br/&gt;&lt;p&gt;With x-ray absorption spectroscopy and x-ray magnetic circular dichroism, the element-specific electronic structure and the magnetic interactions of the double perovskite compounds ${\mathrm{PrCo}}_{0.5}{\mathrm{Ni}}_{0.5}{\mathrm{O}}_{3}$ and ${\mathrm{LaCo}}_{0.5}{\mathrm{Ni}}_{0.5}{\mathrm{O}}_{3…&lt;/p&gt;&lt;br/&gt;[Phys. Rev. B 113, 035131] Published Fri Jan 16, 2026</description>
    <content:encoded>&lt;p&gt;Author(s): Meng-Jie Huang, Peter Nagel, Andreas Eich, Michael Merz, and Stefan Schuppler&lt;/p&gt;&lt;p&gt;With x-ray absorption spectroscopy and x-ray magnetic circular dichroism, the element-specific electronic structure and the magnetic interactions of the double perovskite compounds &lt;math xmlns="http://www.w3.org/1998/Math/MathML"&gt;&lt;mrow&gt;&lt;msub&gt;&lt;mi&gt;PrCo&lt;/mi&gt;&lt;mrow&gt;&lt;mn&gt;0.5&lt;/mn&gt;&lt;/mrow&gt;&lt;/msub&gt;&lt;msub&gt;&lt;mi&gt;Ni&lt;/mi&gt;&lt;mrow&gt;&lt;mn&gt;0.5&lt;/mn&gt;&lt;/mrow&gt;&lt;/msub&gt;&lt;msub&gt;&lt;mi mathvariant="normal"&gt;O&lt;/mi&gt;&lt;mn&gt;3&lt;/mn&gt;&lt;/msub&gt;&lt;/mrow&gt;&lt;/math&gt; and &lt;math xmlns="http://www.w3.org/1998/Math/MathML"&gt;&lt;mrow&gt;&lt;msub&gt;&lt;mi&gt;LaCo&lt;/mi&gt;&lt;mrow&gt;&lt;mn&gt;0.5&lt;/mn&gt;&lt;/mrow&gt;&lt;/msub&gt;&lt;msub&gt;&lt;mi&gt;Ni&lt;/mi&gt;&lt;mrow&gt;&lt;mn&gt;0.5&lt;/mn&gt;&lt;/mrow&gt;&lt;/msub&gt;&lt;msub&gt;&lt;mi mathvariant="normal"&gt;O&lt;/mi&gt;&lt;mn&gt;3&lt;/mn&gt;&lt;/msub&gt;&lt;/mrow&gt;&lt;/math&gt; were studied. In both compounds, Co and Ni depart from their nominal valence state of…&lt;/p&gt;&lt;br/&gt;&lt;p&gt;[Phys. Rev. B 113, 035131] Published Fri Jan 16, 2026&lt;/p&gt;</content:encoded>
    <dc:title>Local electronic structure and magnetic properties of double-perovskite ${\mathrm{LaCo}}_{0.5}{\mathrm{Ni}}_{0.5}{\mathrm{O}}_{3}$ and ${\mathrm{PrCo}}_{0.5}{\mathrm{Ni}}_{0.5}{\mathrm{O}}_{3}$</dc:title>
    <dc:creator>Meng-Jie Huang, Peter Nagel, Andreas Eich, Michael Merz, and Stefan Schuppler</dc:creator>
    <dc:date>2026-01-16T10:00:00+00:00</dc:date>
    <dc:rights>Personal use only, all commercial or other reuse prohibited</dc:rights>
    <dc:source>Phys. Rev. B 113, 035131 (2026)</dc:source>
    <dc:type>article</dc:type>
    <dc:identifier>doi:10.1103/7j4m-g6nh</dc:identifier>
    <prism:doi>10.1103/7j4m-g6nh</prism:doi>
    <prism:publicationName>Physical Review B</prism:publicationName>
    <prism:volume>113</prism:volume>
    <prism:number>3</prism:number>
    <prism:publicationDate>2026-01-16T10:00:00+00:00</prism:publicationDate>
    <prism:url>http://link.aps.org/doi/10.1103/7j4m-g6nh</prism:url>
    <prism:startingPage>035131</prism:startingPage>
    <dc:subject>Electronic structure and strongly correlated systems</dc:subject>
    <prism:section>Electronic structure and strongly correlated systems</prism:section>
  </item>
  <item rdf:about="http://link.aps.org/doi/10.1103/2q6v-4brs">
    <title>Correlated phases in rhombohedral multilayer graphene</title>
    <link>http://link.aps.org/doi/10.1103/2q6v-4brs</link>
    <description>Author(s): Arsen Herasymchuk, Sergei G. Sharapov, Oleg V. Yazyev, and Yaroslav Zhumagulov&lt;br/&gt;&lt;p&gt;We investigate the emergence of correlated electron phases in rhombohedral $N$-layer graphene due to two-valley Coulomb interactions within a low-energy $k·p$ framework. Analytical expressions for Lindhard susceptibilities in intra- and intervalley channels are derived, and the critical temperatures…&lt;/p&gt;&lt;br/&gt;[Phys. Rev. B 113, 035132] Published Fri Jan 16, 2026</description>
    <content:encoded>&lt;p&gt;Author(s): Arsen Herasymchuk, Sergei G. Sharapov, Oleg V. Yazyev, and Yaroslav Zhumagulov&lt;/p&gt;&lt;p&gt;We investigate the emergence of correlated electron phases in rhombohedral &lt;math xmlns="http://www.w3.org/1998/Math/MathML"&gt;&lt;mi&gt;N&lt;/mi&gt;&lt;/math&gt;-layer graphene due to two-valley Coulomb interactions within a low-energy &lt;math xmlns="http://www.w3.org/1998/Math/MathML"&gt;&lt;mrow&gt;&lt;mi&gt;k&lt;/mi&gt;&lt;mo&gt;·&lt;/mo&gt;&lt;mi&gt;p&lt;/mi&gt;&lt;/mrow&gt;&lt;/math&gt; framework. Analytical expressions for Lindhard susceptibilities in intra- and intervalley channels are derived, and the critical temperatures for…&lt;/p&gt;&lt;br/&gt;&lt;p&gt;[Phys. Rev. B 113, 035132] Published Fri Jan 16, 2026&lt;/p&gt;</content:encoded>
    <dc:title>Correlated phases in rhombohedral multilayer graphene</dc:title>
    <dc:creator>Arsen Herasymchuk, Sergei G. Sharapov, Oleg V. Yazyev, and Yaroslav Zhumagulov</dc:creator>
    <dc:date>2026-01-16T10:00:00+00:00</dc:date>
    <dc:rights>Personal use only, all commercial or other reuse prohibited</dc:rights>
    <dc:source>Phys. Rev. B 113, 035132 (2026)</dc:source>
    <dc:type>article</dc:type>
    <dc:identifier>doi:10.1103/2q6v-4brs</dc:identifier>
    <prism:doi>10.1103/2q6v-4brs</prism:doi>
    <prism:publicationName>Physical Review B</prism:publicationName>
    <prism:volume>113</prism:volume>
    <prism:number>3</prism:number>
    <prism:publicationDate>2026-01-16T10:00:00+00:00</prism:publicationDate>
    <prism:url>http://link.aps.org/doi/10.1103/2q6v-4brs</prism:url>
    <prism:startingPage>035132</prism:startingPage>
    <dc:subject>Electronic structure and strongly correlated systems</dc:subject>
    <prism:section>Electronic structure and strongly correlated systems</prism:section>
  </item>
  <item rdf:about="http://link.aps.org/doi/10.1103/m5wt-1hx4">
    <title>Anomalous thermal conductivity enhancement in twisted graphene/$h$-BN bilayers revealed by neuroevolution potential driven atomistic simulations</title>
    <link>http://link.aps.org/doi/10.1103/m5wt-1hx4</link>
    <description>Author(s): Ningxi Yang, Jincheng Yue, Xinkai Sun, Yinong Liu, Meng An, and Shiqian Hu&lt;br/&gt;&lt;p&gt;Twist engineering in van der Waals heterostructures has unlocked a range of novel physical phenomena, yet its influence on lattice thermal transport—particularly in heterostructures—remains underexplored. In this study, we employ a neuroevolution potential (NEP) based atomistic framework, combining …&lt;/p&gt;&lt;br/&gt;[Phys. Rev. B 113, 035426] Published Fri Jan 16, 2026</description>
    <content:encoded>&lt;p&gt;Author(s): Ningxi Yang, Jincheng Yue, Xinkai Sun, Yinong Liu, Meng An, and Shiqian Hu&lt;/p&gt;&lt;p&gt;Twist engineering in van der Waals heterostructures has unlocked a range of novel physical phenomena, yet its influence on lattice thermal transport—particularly in heterostructures—remains underexplored. In this study, we employ a neuroevolution potential (NEP) based atomistic framework, combining …&lt;/p&gt;&lt;br/&gt;&lt;p&gt;[Phys. Rev. B 113, 035426] Published Fri Jan 16, 2026&lt;/p&gt;</content:encoded>
    <dc:title>Anomalous thermal conductivity enhancement in twisted graphene/$h$-BN bilayers revealed by neuroevolution potential driven atomistic simulations</dc:title>
    <dc:creator>Ningxi Yang, Jincheng Yue, Xinkai Sun, Yinong Liu, Meng An, and Shiqian Hu</dc:creator>
    <dc:date>2026-01-16T10:00:00+00:00</dc:date>
    <dc:rights>Personal use only, all commercial or other reuse prohibited</dc:rights>
    <dc:source>Phys. Rev. B 113, 035426 (2026)</dc:source>
    <dc:type>article</dc:type>
    <dc:identifier>doi:10.1103/m5wt-1hx4</dc:identifier>
    <prism:doi>10.1103/m5wt-1hx4</prism:doi>
    <prism:publicationName>Physical Review B</prism:publicationName>
    <prism:volume>113</prism:volume>
    <prism:number>3</prism:number>
    <prism:publicationDate>2026-01-16T10:00:00+00:00</prism:publicationDate>
    <prism:url>http://link.aps.org/doi/10.1103/m5wt-1hx4</prism:url>
    <prism:startingPage>035426</prism:startingPage>
    <dc:subject>Surface physics, nanoscale physics, low-dimensional systems</dc:subject>
    <prism:section>Surface physics, nanoscale physics, low-dimensional systems</prism:section>
  </item>
  <item rdf:about="http://link.aps.org/doi/10.1103/5fp5-xd6m">
    <title>Electronic structure of the kagome compound ${\mathrm{CaTi}}_{3}{\mathrm{Bi}}_{4}$ using high-field torque magnetometry and density functional theory</title>
    <link>http://link.aps.org/doi/10.1103/5fp5-xd6m</link>
    <description>Author(s): Kyryl Shtefiienko, Cole Phillips, Brenden R. Ortiz, David E. Graf, and Keshav Shrestha&lt;br/&gt;&lt;p&gt;We report systematic torque magnetometry measurements to investigate the electronic properties of the newly discovered kagome compound ${\mathrm{CaTi}}_{3}{\mathrm{Bi}}_{4}$. Electrical transport, magnetic susceptibility, and thermal measurements reveal no evidence of a magnetic ground state in this…&lt;/p&gt;&lt;br/&gt;[Phys. Rev. B 113, 045128] Published Fri Jan 16, 2026</description>
    <content:encoded>&lt;p&gt;Author(s): Kyryl Shtefiienko, Cole Phillips, Brenden R. Ortiz, David E. Graf, and Keshav Shrestha&lt;/p&gt;&lt;p&gt;We report systematic torque magnetometry measurements to investigate the electronic properties of the newly discovered kagome compound &lt;math xmlns="http://www.w3.org/1998/Math/MathML"&gt;&lt;mrow&gt;&lt;msub&gt;&lt;mi&gt;CaTi&lt;/mi&gt;&lt;mn&gt;3&lt;/mn&gt;&lt;/msub&gt;&lt;msub&gt;&lt;mi&gt;Bi&lt;/mi&gt;&lt;mn&gt;4&lt;/mn&gt;&lt;/msub&gt;&lt;/mrow&gt;&lt;/math&gt;. Electrical transport, magnetic susceptibility, and thermal measurements reveal no evidence of a magnetic ground state in this material. Torque data obtaine…&lt;/p&gt;&lt;br/&gt;&lt;p&gt;[Phys. Rev. B 113, 045128] Published Fri Jan 16, 2026&lt;/p&gt;</content:encoded>
    <dc:title>Electronic structure of the kagome compound ${\mathrm{CaTi}}_{3}{\mathrm{Bi}}_{4}$ using high-field torque magnetometry and density functional theory</dc:title>
    <dc:creator>Kyryl Shtefiienko, Cole Phillips, Brenden R. Ortiz, David E. Graf, and Keshav Shrestha</dc:creator>
    <dc:date>2026-01-16T10:00:00+00:00</dc:date>
    <dc:rights>Personal use only, all commercial or other reuse prohibited</dc:rights>
    <dc:source>Phys. Rev. B 113, 045128 (2026)</dc:source>
    <dc:type>article</dc:type>
    <dc:identifier>doi:10.1103/5fp5-xd6m</dc:identifier>
    <prism:doi>10.1103/5fp5-xd6m</prism:doi>
    <prism:publicationName>Physical Review B</prism:publicationName>
    <prism:volume>113</prism:volume>
    <prism:number>4</prism:number>
    <prism:publicationDate>2026-01-16T10:00:00+00:00</prism:publicationDate>
    <prism:url>http://link.aps.org/doi/10.1103/5fp5-xd6m</prism:url>
    <prism:startingPage>045128</prism:startingPage>
    <dc:subject>Electronic structure and strongly correlated systems</dc:subject>
    <prism:section>Electronic structure and strongly correlated systems</prism:section>
  </item>
  <item rdf:about="http://link.aps.org/doi/10.1103/gt73-dggf">
    <title>Structural reassessment and emergent altermagnetism of MnS under high pressure</title>
    <link>http://link.aps.org/doi/10.1103/gt73-dggf</link>
    <description>Author(s): Jing Zhao, Shuaiqi Ma, Bingqing Cao, Wenfeng Wu, Guo Chen, Pei Wang, and Xianlong Wang&lt;br/&gt;&lt;p&gt;A comprehensive theoretical study of MnS is conducted using linear response constrained density functional theory to determine the Hubbard $U$ parameter, structure searching to predict high-pressure phases, and first-principles calculations to investigate phase transition behavior and electronic str…&lt;/p&gt;&lt;br/&gt;[Phys. Rev. B 113, 014109] Published Thu Jan 15, 2026</description>
    <content:encoded>&lt;p&gt;Author(s): Jing Zhao, Shuaiqi Ma, Bingqing Cao, Wenfeng Wu, Guo Chen, Pei Wang, and Xianlong Wang&lt;/p&gt;&lt;p&gt;A comprehensive theoretical study of MnS is conducted using linear response constrained density functional theory to determine the Hubbard &lt;math xmlns="http://www.w3.org/1998/Math/MathML"&gt;&lt;mi&gt;U&lt;/mi&gt;&lt;/math&gt; parameter, structure searching to predict high-pressure phases, and first-principles calculations to investigate phase transition behavior and electronic struc…&lt;/p&gt;&lt;br/&gt;&lt;p&gt;[Phys. Rev. B 113, 014109] Published Thu Jan 15, 2026&lt;/p&gt;</content:encoded>
    <dc:title>Structural reassessment and emergent altermagnetism of MnS under high pressure</dc:title>
    <dc:creator>Jing Zhao, Shuaiqi Ma, Bingqing Cao, Wenfeng Wu, Guo Chen, Pei Wang, and Xianlong Wang</dc:creator>
    <dc:date>2026-01-15T10:00:00+00:00</dc:date>
    <dc:rights>Personal use only, all commercial or other reuse prohibited</dc:rights>
    <dc:source>Phys. Rev. B 113, 014109 (2026)</dc:source>
    <dc:type>article</dc:type>
    <dc:identifier>doi:10.1103/gt73-dggf</dc:identifier>
    <prism:doi>10.1103/gt73-dggf</prism:doi>
    <prism:publicationName>Physical Review B</prism:publicationName>
    <prism:volume>113</prism:volume>
    <prism:number>1</prism:number>
    <prism:publicationDate>2026-01-15T10:00:00+00:00</prism:publicationDate>
    <prism:url>http://link.aps.org/doi/10.1103/gt73-dggf</prism:url>
    <prism:startingPage>014109</prism:startingPage>
    <dc:subject>Structure, structural phase transitions, mechanical properties, defects</dc:subject>
    <prism:section>Structure, structural phase transitions, mechanical properties, defects</prism:section>
  </item>
  <item rdf:about="http://link.aps.org/doi/10.1103/q2lp-ffhf">
    <title>Proximity-induced spin-orbit torque in graphene on a trigonal CrSBr monolayer</title>
    <link>http://link.aps.org/doi/10.1103/q2lp-ffhf</link>
    <description>Author(s): Maedeh Rassekh and Martin Gmitra&lt;br/&gt;&lt;p&gt;We present a first-principles and quantum transport study of proximity-induced spin-orbit torque (SOT) in graphene on a trigonal CrSBr monolayer. Density functional theory combined with nonequilibrium Green's function calculations shows that the CrSBr substrate induces spin polarization and a sizabl…&lt;/p&gt;&lt;br/&gt;[Phys. Rev. B 113, 035126] Published Thu Jan 15, 2026</description>
    <content:encoded>&lt;p&gt;Author(s): Maedeh Rassekh and Martin Gmitra&lt;/p&gt;&lt;p&gt;We present a first-principles and quantum transport study of proximity-induced spin-orbit torque (SOT) in graphene on a trigonal CrSBr monolayer. Density functional theory combined with nonequilibrium Green's function calculations shows that the CrSBr substrate induces spin polarization and a sizabl…&lt;/p&gt;&lt;br/&gt;&lt;p&gt;[Phys. Rev. B 113, 035126] Published Thu Jan 15, 2026&lt;/p&gt;</content:encoded>
    <dc:title>Proximity-induced spin-orbit torque in graphene on a trigonal CrSBr monolayer</dc:title>
    <dc:creator>Maedeh Rassekh and Martin Gmitra</dc:creator>
    <dc:date>2026-01-15T10:00:00+00:00</dc:date>
    <dc:rights>Personal use only, all commercial or other reuse prohibited</dc:rights>
    <dc:source>Phys. Rev. B 113, 035126 (2026)</dc:source>
    <dc:type>article</dc:type>
    <dc:identifier>doi:10.1103/q2lp-ffhf</dc:identifier>
    <prism:doi>10.1103/q2lp-ffhf</prism:doi>
    <prism:publicationName>Physical Review B</prism:publicationName>
    <prism:volume>113</prism:volume>
    <prism:number>3</prism:number>
    <prism:publicationDate>2026-01-15T10:00:00+00:00</prism:publicationDate>
    <prism:url>http://link.aps.org/doi/10.1103/q2lp-ffhf</prism:url>
    <prism:startingPage>035126</prism:startingPage>
    <dc:subject>Electronic structure and strongly correlated systems</dc:subject>
    <prism:section>Electronic structure and strongly correlated systems</prism:section>
  </item>
  <item rdf:about="http://link.aps.org/doi/10.1103/jnjq-clrk">
    <title>SU(4) Kondo lattice in semiconductor moiré materials</title>
    <link>http://link.aps.org/doi/10.1103/jnjq-clrk</link>
    <description>Author(s): Sunghoon Kim&lt;br/&gt;&lt;p&gt;Motivated by recent advances in transition metal dichalcogenide (TMD) moiré materials, we propose TMD moiré multilayers as a platform for realizing an approximately SU(4)-symmetric triangular Kondo lattice, generalizing the concept of the double quantum dot model. Our model extends the conventional …&lt;/p&gt;&lt;br/&gt;[Phys. Rev. B 113, 035127] Published Thu Jan 15, 2026</description>
    <content:encoded>&lt;p&gt;Author(s): Sunghoon Kim&lt;/p&gt;&lt;p&gt;Motivated by recent advances in transition metal dichalcogenide (TMD) moiré materials, we propose TMD moiré multilayers as a platform for realizing an approximately SU(4)-symmetric triangular Kondo lattice, generalizing the concept of the double quantum dot model. Our model extends the conventional …&lt;/p&gt;&lt;br/&gt;&lt;p&gt;[Phys. Rev. B 113, 035127] Published Thu Jan 15, 2026&lt;/p&gt;</content:encoded>
    <dc:title>SU(4) Kondo lattice in semiconductor moiré materials</dc:title>
    <dc:creator>Sunghoon Kim</dc:creator>
    <dc:date>2026-01-15T10:00:00+00:00</dc:date>
    <dc:rights>Personal use only, all commercial or other reuse prohibited</dc:rights>
    <dc:source>Phys. Rev. B 113, 035127 (2026)</dc:source>
    <dc:type>article</dc:type>
    <dc:identifier>doi:10.1103/jnjq-clrk</dc:identifier>
    <prism:doi>10.1103/jnjq-clrk</prism:doi>
    <prism:publicationName>Physical Review B</prism:publicationName>
    <prism:volume>113</prism:volume>
    <prism:number>3</prism:number>
    <prism:publicationDate>2026-01-15T10:00:00+00:00</prism:publicationDate>
    <prism:url>http://link.aps.org/doi/10.1103/jnjq-clrk</prism:url>
    <prism:startingPage>035127</prism:startingPage>
    <dc:subject>Electronic structure and strongly correlated systems</dc:subject>
    <prism:section>Electronic structure and strongly correlated systems</prism:section>
  </item>
  <item rdf:about="http://link.aps.org/doi/10.1103/pt16-43yd">
    <title>Low-energy photoexcitations inside the Mott gap in doped Hubbard and $t\text{−}J$ ladders</title>
    <link>http://link.aps.org/doi/10.1103/pt16-43yd</link>
    <description>Author(s): Sumal Chandra, Kazuya Shinjo, Shigetoshi Sota, Seiji Yunoki, and Takami Tohyama&lt;br/&gt;&lt;p&gt;We investigate changes in the optical conductivity of doped Mott insulators by tuning ultrashort pump pulses to target either the Drude or low-energy absorption regions. Using a hole-doped two-leg Hubbard ladder and a four-leg $t\text{−}J$ ladder, we calculate the optical conductivity after pumping …&lt;/p&gt;&lt;br/&gt;[Phys. Rev. B 113, 045127] Published Thu Jan 15, 2026</description>
    <content:encoded>&lt;p&gt;Author(s): Sumal Chandra, Kazuya Shinjo, Shigetoshi Sota, Seiji Yunoki, and Takami Tohyama&lt;/p&gt;&lt;p&gt;We investigate changes in the optical conductivity of doped Mott insulators by tuning ultrashort pump pulses to target either the Drude or low-energy absorption regions. Using a hole-doped two-leg Hubbard ladder and a four-leg &lt;math xmlns="http://www.w3.org/1998/Math/MathML"&gt;&lt;mrow&gt;&lt;mi&gt;t&lt;/mi&gt;&lt;mtext&gt;−&lt;/mtext&gt;&lt;mi&gt;J&lt;/mi&gt;&lt;/mrow&gt;&lt;/math&gt; ladder, we calculate the optical conductivity after pumping by employ…&lt;/p&gt;&lt;br/&gt;&lt;p&gt;[Phys. Rev. B 113, 045127] Published Thu Jan 15, 2026&lt;/p&gt;</content:encoded>
    <dc:title>Low-energy photoexcitations inside the Mott gap in doped Hubbard and $t\text{−}J$ ladders</dc:title>
    <dc:creator>Sumal Chandra, Kazuya Shinjo, Shigetoshi Sota, Seiji Yunoki, and Takami Tohyama</dc:creator>
    <dc:date>2026-01-15T10:00:00+00:00</dc:date>
    <dc:rights>Personal use only, all commercial or other reuse prohibited</dc:rights>
    <dc:source>Phys. Rev. B 113, 045127 (2026)</dc:source>
    <dc:type>article</dc:type>
    <dc:identifier>doi:10.1103/pt16-43yd</dc:identifier>
    <prism:doi>10.1103/pt16-43yd</prism:doi>
    <prism:publicationName>Physical Review B</prism:publicationName>
    <prism:volume>113</prism:volume>
    <prism:number>4</prism:number>
    <prism:publicationDate>2026-01-15T10:00:00+00:00</prism:publicationDate>
    <prism:url>http://link.aps.org/doi/10.1103/pt16-43yd</prism:url>
    <prism:startingPage>045127</prism:startingPage>
    <dc:subject>Electronic structure and strongly correlated systems</dc:subject>
    <prism:section>Electronic structure and strongly correlated systems</prism:section>
  </item>
  <item rdf:about="http://link.aps.org/doi/10.1103/jyfh-q2r7">
    <title>Radial Rashba spin-orbit fields in commensurate twisted transition metal dichalcogenide bilayers</title>
    <link>http://link.aps.org/doi/10.1103/jyfh-q2r7</link>
    <description>Author(s): Thomas Naimer, Paulo E. Faria Junior, Klaus Zollner, and Jaroslav Fabian&lt;br/&gt;&lt;p&gt;The authors investigate here predominantly radial in-plane spin-orbit fields in twisted transition metal dichalcogenide homobilayers (NbSe&lt;math xmlns="http://www.w3.org/1998/Math/MathML" display="inline"&gt;&lt;msub&gt;&lt;mrow&gt;&lt;/mrow&gt;&lt;mn&gt;2&lt;/mn&gt;&lt;/msub&gt;&lt;/math&gt;, WSe&lt;math xmlns="http://www.w3.org/1998/Math/MathML" display="inline"&gt;&lt;msub&gt;&lt;mrow&gt;&lt;/mrow&gt;&lt;mn&gt;2&lt;/mn&gt;&lt;/msub&gt;&lt;/math&gt;, and WTe&lt;math xmlns="http://www.w3.org/1998/Math/MathML" display="inline"&gt;&lt;msub&gt;&lt;mrow&gt;&lt;/mrow&gt;&lt;mn&gt;2&lt;/mn&gt;&lt;/msub&gt;&lt;/math&gt;) using density functional theory. Their results highlight the crucial role of the 180&lt;math xmlns="http://www.w3.org/1998/Math/MathML" display="inline"&gt;&lt;msup&gt;&lt;mrow&gt;&lt;/mrow&gt;&lt;mtext&gt;o&lt;/mtext&gt;&lt;/msup&gt;&lt;/math&gt; in-plane rotational symmetry as well as the dependence on the size of the commensurate supercell. By fitting the first-principles results to an effective model Hamiltonian, the authors extract the twist-angle-dependent and supercell-size-dependent parameters governing the spin-orbit fields, relevant for designing spintronic devices.&lt;/p&gt;&lt;img src="//cdn.journals.aps.org/journals/PRB/key_images/10.1103/jyfh-q2r7.png" width="200" height=\"100\"&gt;&lt;br/&gt;[Phys. Rev. B 113, 045417] Published Thu Jan 15, 2026</description>
    <content:encoded>&lt;p&gt;Author(s): Thomas Naimer, Paulo E. Faria Junior, Klaus Zollner, and Jaroslav Fabian&lt;/p&gt;&lt;p&gt;The authors investigate here predominantly radial in-plane spin-orbit fields in twisted transition metal dichalcogenide homobilayers (NbSe&lt;math xmlns="http://www.w3.org/1998/Math/MathML" display="inline"&gt;&lt;msub&gt;&lt;mrow&gt;&lt;/mrow&gt;&lt;mn&gt;2&lt;/mn&gt;&lt;/msub&gt;&lt;/math&gt;, WSe&lt;math xmlns="http://www.w3.org/1998/Math/MathML" display="inline"&gt;&lt;msub&gt;&lt;mrow&gt;&lt;/mrow&gt;&lt;mn&gt;2&lt;/mn&gt;&lt;/msub&gt;&lt;/math&gt;, and WTe&lt;math xmlns="http://www.w3.org/1998/Math/MathML" display="inline"&gt;&lt;msub&gt;&lt;mrow&gt;&lt;/mrow&gt;&lt;mn&gt;2&lt;/mn&gt;&lt;/msub&gt;&lt;/math&gt;) using density functional theory. Their results highlight the crucial role of the 180&lt;math xmlns="http://www.w3.org/1998/Math/MathML" display="inline"&gt;&lt;msup&gt;&lt;mrow&gt;&lt;/mrow&gt;&lt;mtext&gt;o&lt;/mtext&gt;&lt;/msup&gt;&lt;/math&gt; in-plane rotational symmetry as well as the dependence on the size of the commensurate supercell. By fitting the first-principles results to an effective model Hamiltonian, the authors extract the twist-angle-dependent and supercell-size-dependent parameters governing the spin-orbit fields, relevant for designing spintronic devices.&lt;/p&gt;&lt;img src="//cdn.journals.aps.org/journals/PRB/key_images/10.1103/jyfh-q2r7.png" width="200" height=\"100\"&gt;&lt;br/&gt;&lt;p&gt;[Phys. Rev. B 113, 045417] Published Thu Jan 15, 2026&lt;/p&gt;</content:encoded>
    <dc:title>Radial Rashba spin-orbit fields in commensurate twisted transition metal dichalcogenide bilayers</dc:title>
    <dc:creator>Thomas Naimer, Paulo E. Faria Junior, Klaus Zollner, and Jaroslav Fabian</dc:creator>
    <dc:date>2026-01-15T10:00:00+00:00</dc:date>
    <dc:rights>Personal use only, all commercial or other reuse prohibited</dc:rights>
    <dc:source>Phys. Rev. B 113, 045417 (2026)</dc:source>
    <dc:type>article</dc:type>
    <dc:identifier>doi:10.1103/jyfh-q2r7</dc:identifier>
    <prism:doi>10.1103/jyfh-q2r7</prism:doi>
    <prism:publicationName>Physical Review B</prism:publicationName>
    <prism:volume>113</prism:volume>
    <prism:number>4</prism:number>
    <prism:publicationDate>2026-01-15T10:00:00+00:00</prism:publicationDate>
    <prism:url>http://link.aps.org/doi/10.1103/jyfh-q2r7</prism:url>
    <prism:startingPage>045417</prism:startingPage>
    <dc:subject>Surface physics, nanoscale physics, low-dimensional systems</dc:subject>
    <prism:section>Surface physics, nanoscale physics, low-dimensional systems</prism:section>
  </item>
  <item rdf:about="http://link.aps.org/doi/10.1103/blkg-3t1v">
    <title>On the topological dual of the XXZ spin chain</title>
    <link>http://link.aps.org/doi/10.1103/blkg-3t1v</link>
    <description>Author(s): Yicheng Tang, Pradip Kattel, and Natan Andrei&lt;br/&gt;&lt;p&gt;The spin-½ XXZ chain is a well-known model of spontaneous symmetry breaking. But what is its symmetry-protected topological dual model? Here, the authors construct a fermionic dual model via a modified Jordan–Wigner transformation. They demonstrate its topological nature through exact string order parameters, entanglement spectrum degeneracies, and Majorana zero modes, and identify the duals of the ferromagnetic and antiferromagnetic phases as two distinct topological phases separated by an extended Luttinger liquid regime.&lt;/p&gt;&lt;img src="//cdn.journals.aps.org/journals/PRB/key_images/10.1103/blkg-3t1v.png" width="200" height=\"100\"&gt;&lt;br/&gt;[Phys. Rev. B 113, L041113] Published Thu Jan 15, 2026</description>
    <content:encoded>&lt;p&gt;Author(s): Yicheng Tang, Pradip Kattel, and Natan Andrei&lt;/p&gt;&lt;p&gt;The spin-½ XXZ chain is a well-known model of spontaneous symmetry breaking. But what is its symmetry-protected topological dual model? Here, the authors construct a fermionic dual model via a modified Jordan–Wigner transformation. They demonstrate its topological nature through exact string order parameters, entanglement spectrum degeneracies, and Majorana zero modes, and identify the duals of the ferromagnetic and antiferromagnetic phases as two distinct topological phases separated by an extended Luttinger liquid regime.&lt;/p&gt;&lt;img src="//cdn.journals.aps.org/journals/PRB/key_images/10.1103/blkg-3t1v.png" width="200" height=\"100\"&gt;&lt;br/&gt;&lt;p&gt;[Phys. Rev. B 113, L041113] Published Thu Jan 15, 2026&lt;/p&gt;</content:encoded>
    <dc:title>On the topological dual of the XXZ spin chain</dc:title>
    <dc:creator>Yicheng Tang, Pradip Kattel, and Natan Andrei</dc:creator>
    <dc:date>2026-01-15T10:00:00+00:00</dc:date>
    <dc:rights>Personal use only, all commercial or other reuse prohibited</dc:rights>
    <dc:source>Phys. Rev. B 113, L041113 (2026)</dc:source>
    <dc:type>article</dc:type>
    <dc:identifier>doi:10.1103/blkg-3t1v</dc:identifier>
    <prism:doi>10.1103/blkg-3t1v</prism:doi>
    <prism:publicationName>Physical Review B</prism:publicationName>
    <prism:volume>113</prism:volume>
    <prism:number>4</prism:number>
    <prism:publicationDate>2026-01-15T10:00:00+00:00</prism:publicationDate>
    <prism:url>http://link.aps.org/doi/10.1103/blkg-3t1v</prism:url>
    <prism:startingPage>L041113</prism:startingPage>
    <dc:subject>Electronic structure and strongly correlated systems</dc:subject>
    <prism:section>Electronic structure and strongly correlated systems</prism:section>
  </item>
  </rdf:RDF>
